Metadata-Version: 1.0
Name: tipfy.ext.jsonrpc
Version: 0.1
Summary: Tipfy extension to create JSON-RPC services
Home-page: http://www.tipfy.org/
Author: Rodrigo Moraes
Author-email: rodrigo.moraes@gmail.com
License: Apache
Platform: any
Classifier: Development Status :: 4 - Beta
Classifier: Environment :: Web Environment
Classifier: Intended Audience :: Developers
Classifier: License :: OSI Approved :: Apache Software License
Classifier: Operating System :: OS Independent
Classifier: Programming Language :: Python
Classifier: Topic :: Internet :: WWW/HTTP :: Dynamic Content
Classifier: Topic :: Software Development :: Libraries :: Python Modules
